export_chapters/__init__.py
export_chapters/cli.py
export_chapters-0.1.7.dist-info/licenses/LICENSE
export_chapters-0.1.7.dist-info/METADATA
export_chapters-0.1.7.dist-info/WHEEL
export_chapters-0.1.7.dist-info/entry_points.txt
export_chapters-0.1.7.dist-info/top_level.txt
export_chapters-0.1.7.dist-info/RECORD
