Metadata-Version: 2.4
Name: export-chapters
Version: 0.1.7
Summary: Export MP4/MOV chapter markers into YouTube description-friendly text
Author: Your Name
License: MIT
Requires-Python: >=3.8
License-File: LICENSE
Dynamic: license-file
